git_record/__init__.py
git_record/git_record.py
git_record_svtter-0.0.2.dist-info/LICENSE
git_record_svtter-0.0.2.dist-info/METADATA
git_record_svtter-0.0.2.dist-info/WHEEL
git_record_svtter-0.0.2.dist-info/entry_points.txt
git_record_svtter-0.0.2.dist-info/top_level.txt
git_record_svtter-0.0.2.dist-info/RECORD
