Metadata-Version: 2.1
Name: git-record-svtter
Version: 0.0.2
Summary: A tools to record temporal code
Home-page: https://github.com/Svtter/git_record
Author: svtter
Author-email: svtter@qq.com
License: UNKNOWN
Platform: UNKNOWN
Classifier: Programming Language :: Python :: 3
Classifier: License :: OSI Approved :: MIT License
Classifier: Operating System :: OS Independent
Requires-Python: >=3.6
Requires-Dist: gitpython
Requires-Dist: arrow
